pyfasttrack/__init__.py
pyfasttrack/base_detector.py
pyfasttrack/data.py
pyfasttrack/example.py
pyfasttrack/example_yolo.py
pyfasttrack/ft_detector.py
pyfasttrack/tracker.py
pyfasttrack/yolo_detector.py
pyfasttrack-0.0.3.dist-info/LICENSE
pyfasttrack-0.0.3.dist-info/METADATA
pyfasttrack-0.0.3.dist-info/WHEEL
pyfasttrack-0.0.3.dist-info/top_level.txt
pyfasttrack-0.0.3.dist-info/RECORD
